setup.py
GBa222distributions/Binomialdistribution.py
GBa222distributions/Gaussiandistribution.py
GBa222distributions/Generaldistribution.py
GBa222distributions/__init__.py
GBa222distributions.egg-info/PKG-INFO
GBa222distributions.egg-info/SOURCES.txt
GBa222distributions.egg-info/dependency_links.txt
GBa222distributions.egg-info/not-zip-safe
GBa222distributions.egg-info/top_level.txt